{
  "project_info": {
    "project_number": "859175072247",
    "project_id": "pak-scrap",
    "storage_bucket": "pak-scrap.firebasestorage.app"
  },
  "client": [
    {
      "client_info": {
        "mobilesdk_app_id": "1:859175072247:android:46f10c86f63a62e6c5bef2",
        "android_client_info": {
          "package_name": "com.pakscrap"
        }
      },
      "oauth_client": [],
      "api_key": [
        {
          "current_key": "AIzaSyBA7leWftlw4oP6a_o2Py0sHbgz-opD780"
        }
      ],
      "services": {
        "appinvite_service": {
          "other_platform_oauth_client": []
        }
      },
      "admob_app_id": "ca-app-pub-2684750191705026~9772782341"
    }
  ],
  "configuration_version": "1"
}